{
  "workId": "romulus",
  "subject": "Romulus",
  "characters": [
    {
      "id": "remus",
      "names": [
        "Remus"
      ],
      "relation": "Twin brother; slain at the founding",
      "blurb": "Twin of Romulus. Captured while raiding Amulius’s herds, then killed—by Romulus or by Celer—when he mocked the new walls.",
      "links": [
        {
          "characterId": "amulius"
        },
        {
          "characterId": "celer"
        },
        {
          "characterId": "faustulus"
        },
        {
          "characterId": "pirithous",
          "label": "Theseus’s Life",
          "workId": "theseus"
        }
      ]
    },
    {
      "id": "numitor",
      "names": [
        "Numitor"
      ],
      "relation": "Maternal grandfather; rightful king of Alba",
      "blurb": "Deposed by Amulius, he recognized the twins and with them recovered Alba Longa before they founded Rome.",
      "links": [
        {
          "characterId": "amulius"
        },
        {
          "characterId": "remus"
        }
      ]
    },
    {
      "id": "amulius",
      "names": [
        "Amulius"
      ],
      "relation": "Usurping great-uncle at Alba",
      "blurb": "Seized Numitor’s throne, forced Rhea Silvia into Vestal vows, and ordered the twins drowned. They returned and killed him.",
      "links": [
        {
          "characterId": "numitor"
        },
        {
          "characterId": "rhea-silvia"
        },
        {
          "characterId": "remus"
        }
      ]
    },
    {
      "id": "rhea-silvia",
      "names": [
        "Rhea Silvia",
        "Ilia"
      ],
      "relation": "Mother of the twins",
      "blurb": "Daughter of Numitor, made a Vestal by Amulius. Mars (or a lover) fathered Romulus and Remus upon her.",
      "links": [
        {
          "characterId": "numitor"
        },
        {
          "characterId": "amulius"
        },
        {
          "characterId": "mars"
        }
      ]
    },
    {
      "id": "mars",
      "names": [
        "Mars"
      ],
      "relation": "Reputed divine father",
      "blurb": "War-god said to have fathered the twins on Rhea Silvia—the pedigree Rome claimed for its martial destiny.",
      "links": [
        {
          "characterId": "rhea-silvia"
        }
      ]
    },
    {
      "id": "faustulus",
      "names": [
        "Faustulus"
      ],
      "relation": "Shepherd foster-father",
      "blurb": "Royal herdsman who found the twins at the fig-tree and raised them with Larentia. He later revealed their birth to Numitor.",
      "links": [
        {
          "characterId": "larentia"
        },
        {
          "characterId": "remus"
        },
        {
          "characterId": "numitor"
        }
      ]
    },
    {
      "id": "larentia",
      "names": [
        "Larentia",
        "Acca Larentia",
        "Acca"
      ],
      "relation": "Foster-mother",
      "blurb": "Wife of Faustulus who nursed the twins. Some say “Lupa” was her nickname as a courtesan; others keep the wolf literal.",
      "links": [
        {
          "characterId": "faustulus"
        }
      ]
    },
    {
      "id": "tatius",
      "names": [
        "Tatius"
      ],
      "relation": "Sabine co-king",
      "blurb": "King of the Sabines who warred on Rome after the rape of the women, then shared the throne with Romulus until he was murdered at Lavinium.",
      "links": [
        {
          "characterId": "hersilia"
        },
        {
          "characterId": "tarpeia"
        }
      ]
    },
    {
      "id": "hersilia",
      "names": [
        "Hersilia"
      ],
      "relation": "Wife; peacemaker with the Sabines",
      "blurb": "Chief among the stolen Sabine women. She begged peace between fathers and husbands and later was said to share Romulus’s divine honors.",
      "links": [
        {
          "characterId": "tatius"
        }
      ]
    },
    {
      "id": "tarpeia",
      "names": [
        "Tarpeia"
      ],
      "relation": "Betrayer of the Capitol",
      "blurb": "Daughter of the citadel’s commander; she opened the gate to Tatius for what the Sabines wore on their left arms—and was crushed under their shields.",
      "links": [
        {
          "characterId": "tatius"
        },
        {
          "characterId": "tarpeius"
        }
      ]
    },
    {
      "id": "tarpeius",
      "names": [
        "Tarpeius"
      ],
      "relation": "Commander of the Capitol",
      "blurb": "Father of Tarpeia; entrusted with the Capitoline when the Sabines attacked. His daughter’s treachery cost Rome the rock.",
      "links": [
        {
          "characterId": "tarpeia"
        },
        {
          "characterId": "tatius"
        }
      ]
    },
    {
      "id": "acron",
      "names": [
        "Acron"
      ],
      "relation": "King of Caenina; first spolia opima",
      "blurb": "Ruler of Caenina who challenged Romulus after the rape. Romulus killed him and dedicated the first spolia opima to Jupiter Feretrius."
    },
    {
      "id": "celer",
      "names": [
        "Celer"
      ],
      "relation": "Wall-guard who may have killed Remus",
      "blurb": "One tradition makes this swift lieutenant, not Romulus, the man who struck Remus for leaping the unfinished wall.",
      "links": [
        {
          "characterId": "remus"
        }
      ]
    },
    {
      "id": "hostilius",
      "names": [
        "Hostilius"
      ],
      "relation": "Early Sabine war casualty; ancestor of Tullus",
      "blurb": "Roman who fell fighting the Sabines; his grandson Tullus Hostilius later became king. Plutarch marks the family among the first mixed houses.",
      "links": [
        {
          "characterId": "tatius"
        },
        {
          "characterId": "tullus",
          "label": "Tullus Hostilius",
          "workId": "numa-pompilius"
        }
      ]
    },
    {
      "id": "aeneas",
      "names": [
        "Aeneas"
      ],
      "relation": "Trojan ancestor of the Alban line",
      "blurb": "Trojan exile whose Italian settlement founded the line of Alba Longa—Numitor, Rhea Silvia, and so the twins.",
      "links": [
        {
          "characterId": "numitor"
        }
      ]
    },
    {
      "id": "evander",
      "names": [
        "Evander"
      ],
      "relation": "Earlier settler on the Palatine",
      "blurb": "Arcadian who held the Palatine before Romulus; his rites of Hercules and the Lupercal color Rome’s oldest cults.",
      "links": [
        {
          "characterId": "hercules"
        }
      ]
    },
    {
      "id": "hercules",
      "names": [
        "Hercules"
      ],
      "relation": "Hero honored at the Ara Maxima",
      "blurb": "Evander’s guest-hero whose altar Romulus’s Rome kept. His cult marks the Greek strand in early Roman religion.",
      "links": [
        {
          "characterId": "evander"
        }
      ]
    },
    {
      "id": "quirinus",
      "names": [
        "Quirinus"
      ],
      "relation": "Divine name after his vanishing",
      "blurb": "The god Romulus became when he disappeared in the storm—or so Proculus Julius swore to the mourning people.",
      "links": [
        {
          "characterId": "proculus"
        }
      ]
    },
    {
      "id": "proculus",
      "names": [
        "Proculus",
        "Proculus Julius",
        "Julius"
      ],
      "relation": "Witness of Romulus’s apotheosis",
      "blurb": "Patrician who swore Romulus met him on the road as Quirinus and ordered the Romans to cultivate arms and know their city would rule.",
      "links": [
        {
          "characterId": "quirinus"
        }
      ]
    },
    {
      "id": "talasius",
      "names": [
        "Talasius"
      ],
      "relation": "Name cried at Roman weddings",
      "blurb": "Companion (or cry) tied to the rape of the Sabine women; Romans later shouted “Talasio” at marriages as a lucky omen.",
      "links": [
        {
          "characterId": "hersilia"
        },
        {
          "characterId": "tatius"
        }
      ]
    },
    {
      "id": "tarchetius",
      "names": [
        "Tarchetius"
      ],
      "relation": "Alternate Alban founder-tale king",
      "blurb": "In one strange variant, an Alban king whose hearth-phallus story rivals the Mars-and-Rhea birth of the twins.",
      "links": [
        {
          "characterId": "tarrutius"
        },
        {
          "characterId": "rhea-silvia"
        }
      ]
    },
    {
      "id": "tarrutius",
      "names": [
        "Tarrutius"
      ],
      "relation": "Husband in the Tarchetius variant",
      "blurb": "Wealthy man married to a handmaid in the alternate birth story Tarchetius’s court produced.",
      "links": [
        {
          "characterId": "tarchetius"
        }
      ]
    },
    {
      "id": "fidenae",
      "names": [
        "Fidenae"
      ],
      "relation": "Neighbor city Romulus took",
      "blurb": "Latin town Romulus seized after it stirred against Rome—one of the early wars that widened his territory.",
      "links": [
        {
          "characterId": "veientes"
        }
      ]
    },
    {
      "id": "veientes",
      "names": [
        "Veientes"
      ],
      "relation": "Etruscan neighbors; early foes",
      "blurb": "People of Veii who fought Romulus after Fidenae fell. Their wars foreshadow Camillus’s later siege.",
      "links": [
        {
          "characterId": "fidenae"
        },
        {
          "characterId": "camillus",
          "label": "Camillus",
          "workId": "camillus"
        }
      ]
    },
    {
      "id": "juba",
      "names": [
        "Juba"
      ],
      "relation": "Historian cited on early Rome",
      "blurb": "Learned king whose antiquarian notes Plutarch quotes among conflicting accounts of Rome’s beginnings."
    },
    {
      "id": "varro",
      "names": [
        "Varro"
      ],
      "relation": "Roman antiquarian cited",
      "blurb": "Marcus Terentius Varro, whose chronology and lore Plutarch weighs against other founders’ dates."
    },
    {
      "id": "romulus",
      "names": [
        "Romulus"
      ],
      "relation": "Founder of Rome; subject of the Life",
      "blurb": "Twin of Remus who traced descent from Mars, slew Remus and Acron, built Rome’s walls, and vanished in a storm to become the god Quirinus.",
      "links": [
        {
          "characterId": "remus"
        },
        {
          "characterId": "mars"
        },
        {
          "characterId": "quirinus"
        },
        {
          "characterId": "proculus"
        }
      ]
    },
    {
      "id": "jupiter",
      "names": [
        "Jupiter",
        "Jupiter Feretrius",
        "Jupiter Stator"
      ],
      "relation": "Chief god; recipient of the first spolia opima",
      "blurb": "Romulus vowed his enemy Acron’s armor to Jupiter Feretrius after Caenina, and prayed to Jupiter Stator to halt the Roman rout in the Sabine war.",
      "links": [
        {
          "characterId": "acron"
        },
        {
          "characterId": "tatius"
        }
      ]
    },
    {
      "id": "carmenta",
      "names": [
        "Carmenta"
      ],
      "relation": "Prophetess; Evander’s mother",
      "blurb": "Prophetic nymph whose oracles Evander carried to Italy; her name means either ‘verse-singer’ from carmen or ‘out of her mind’ for prophetic frenzy.",
      "links": [
        {
          "characterId": "evander"
        }
      ]
    },
    {
      "id": "vulcan",
      "names": [
        "Vulcan"
      ],
      "relation": "God whose temple held the brazen chariot",
      "blurb": "Romulus placed a four-horse chariot from Camerium in the temple of Vulcan; that precinct was later one of the sites named for his disappearance.",
      "links": [
        {
          "characterId": "romulus"
        }
      ]
    },
    {
      "id": "vesta",
      "names": [
        "Vesta"
      ],
      "relation": "Goddess who restrained Amulius; hearth of the city",
      "blurb": "Vesta appeared to Amulius in a dream and dissuaded him from killing Rhea Silvia; her temple on the Sacred Way marked the Sabine truce.",
      "links": [
        {
          "characterId": "amulius"
        },
        {
          "characterId": "rhea-silvia"
        }
      ]
    },
    {
      "id": "romus",
      "names": [
        "Romus"
      ],
      "relation": "Legendary alternate founder figure",
      "blurb": "One variant makes Romus—son of Emathion or king of the Latins—the true eponym of Rome, displacing the Romulus-and-Remus tradition Plutarch examines.",
      "links": [
        {
          "characterId": "aeneas"
        }
      ]
    },
    {
      "id": "diocles",
      "names": [
        "Diocles",
        "Diocles of Peparethus"
      ],
      "relation": "Earliest Greek historian of Rome’s founding",
      "blurb": "Author from Peparethus whom Fabius Pictor follows; together they are Plutarch’s oldest sources for the wolf, the twins, and the founding narrative.",
      "links": [
        {
          "characterId": "fabius-pictor"
        }
      ]
    },
    {
      "id": "fabius-pictor",
      "names": [
        "Fabius Pictor",
        "Fabius"
      ],
      "relation": "Roman annalist; oldest Latin historian",
      "blurb": "Wrote Rome’s founding traditions in Greek; Plutarch weighs his account alongside Diocles of Peparethus for the story of the twins and the Sabine war.",
      "links": [
        {
          "characterId": "diocles"
        }
      ]
    },
    {
      "id": "cossus",
      "names": [
        "Cornelius Cossus",
        "Cossus"
      ],
      "relation": "Second winner of the spolia opima",
      "blurb": "Killed the Etruscan king Tolumnius in single combat and dedicated the second spolia opima to Jupiter Feretrius, following Romulus’s founding precedent.",
      "links": [
        {
          "characterId": "jupiter"
        },
        {
          "characterId": "marcellus-r"
        }
      ]
    },
    {
      "id": "marcellus-r",
      "names": [
        "Claudius Marcellus",
        "Marcellus"
      ],
      "relation": "Third and last winner of the spolia opima",
      "blurb": "Slew the Gallic king Viridomarus and claimed the third spolia opima; later Caesar’s workmen, repairing steps near the trophy, reopened the inscription dispute.",
      "links": [
        {
          "characterId": "cossus"
        },
        {
          "characterId": "caesar-r"
        }
      ]
    },
    {
      "id": "scipio-r",
      "names": [
        "Scipio Africanus",
        "Scipio"
      ],
      "relation": "Parallel figure: great man whose death was unexplained",
      "blurb": "Plutarch invokes Scipio’s mysterious home-death to suggest that Romulus’s disappearance, however strange, is not unique among Rome’s greatest men.",
      "links": [
        {
          "characterId": "romulus"
        }
      ]
    },
    {
      "id": "caesar-r",
      "names": [
        "Caesar"
      ],
      "relation": "Later figure cited in the spolia opima dispute",
      "blurb": "Caius Caesar’s workmen, repairing steps near an ancient trophy site, uncovered an inscription that reopened debate about Cossus’s spolia opima claim.",
      "links": [
        {
          "characterId": "cossus"
        },
        {
          "characterId": "caesar-subject",
          "label": "Caesar’s Life",
          "workId": "caesar"
        }
      ]
    },
    {
      "id": "numa-r",
      "names": [
        "Numa",
        "Numa Pompilius"
      ],
      "relation": "Peaceable successor mentioned in the Life",
      "blurb": "Plutarch notes that the Roman calendar and Vestal order were disputed between Romulus and Numa—the martial founder and the priestly king differ in Plutarch’s comparison.",
      "links": [
        {
          "characterId": "numa-life",
          "label": "Numa’s Life",
          "workId": "numa-pompilius"
        }
      ]
    },
    {
      "id": "aristeas",
      "names": [
        "Aristeas",
        "Aristeas the Proconnesian"
      ],
      "relation": "Greek mythic figure who vanished like Romulus",
      "blurb": "Died in a fuller’s workshop yet was later seen traveling; Plutarch pairs him with Cleomedes as Greek parallels to Romulus’s miraculous translation.",
      "links": [
        {
          "characterId": "cleomedes"
        },
        {
          "characterId": "quirinus"
        }
      ]
    },
    {
      "id": "cleomedes",
      "names": [
        "Cleomedes",
        "Cleomedes the Astypalaean"
      ],
      "relation": "Greek hero who vanished; parallel to Romulus",
      "blurb": "Mighty and wild athlete from Astypalaea who disappeared after a mad act—one of the Greek vanishing-hero tales Plutarch places beside Romulus’s translation.",
      "links": [
        {
          "characterId": "aristeas"
        },
        {
          "characterId": "quirinus"
        }
      ]
    },
    {
      "id": "antigonus",
      "names": [
        "Antigonus"
      ],
      "relation": "Historian who recorded the Tarpeia tradition",
      "blurb": "Cited for the version that Tarpeius arranged his daughter’s treachery himself—a reading Plutarch considers absurd but records among the conflicting accounts.",
      "links": [
        {
          "characterId": "tarpeia"
        },
        {
          "characterId": "tarpeius"
        }
      ]
    },
    {
      "id": "postumius-rom",
      "names": [
        "Postumius"
      ],
      "relation": "Latin commander who menaced Rome after the Gallic sack",
      "blurb": "Livius Postumius led a Latin army against the weakened city; Plutarch records his demand for Roman wives and the ruse of the handmaids that saved Rome.",
      "links": [
        {
          "characterId": "romulus"
        }
      ]
    },
    {
      "id": "dionysius-hal",
      "names": [
        "Dionysius"
      ],
      "relation": "Historian of Rome; cited in triumph dispute",
      "blurb": "Dionysius of Halicarnassus, Greek historian of Rome; Plutarch explicitly corrects him for asserting Romulus rode in a chariot at his triumph—statues of Romulus in Rome show him on foot.",
      "links": [
        {
          "characterId": "romulus"
        }
      ]
    },
    {
      "id": "damaratus",
      "names": [
        "Damaratus"
      ],
      "relation": "Corinthian exile; Tarquinius Priscus's father",
      "blurb": "Wealthy Corinthian who emigrated to Etruria and fathered Tarquinius Priscus; mentioned when Plutarch notes that Tarquinius—not Romulus—was the first to surround the triumph with great pomp.",
      "links": [
        {
          "characterId": "tarquinius-priscus"
        }
      ]
    },
    {
      "id": "tarquinius-priscus",
      "names": [
        "Tarquinius",
        "Tarquin"
      ],
      "relation": "Fifth king of Rome; gave triumphs their pomp",
      "blurb": "Tarquinius Priscus, Damaratus's son and fifth king of Rome; one tradition credits him—rather than Romulus or Publicola—with introducing the magnificent trappings that made the Roman triumph the spectacle it became.",
      "links": [
        {
          "characterId": "damaratus"
        },
        {
          "characterId": "publicola-r"
        }
      ]
    },
    {
      "id": "tolumnius",
      "names": [
        "Tolumnius"
      ],
      "relation": "Etruscan king killed by Cossus; second spolia opima",
      "blurb": "King of Veii whose death at the hands of Cornelius Cossus in single combat earned the second spolia opima in Roman history—following the precedent Romulus set by killing Acron.",
      "links": [
        {
          "characterId": "cossus"
        },
        {
          "characterId": "acron"
        }
      ]
    },
    {
      "id": "viridomarus",
      "names": [
        "Viridomarus"
      ],
      "relation": "Gallic king killed by Marcellus; third spolia opima",
      "blurb": "Gallic chieftain slain by Claudius Marcellus in single combat—earning the third and last spolia opima ever dedicated, completing the trio begun by Romulus's victory over Acron.",
      "links": [
        {
          "characterId": "marcellus-r"
        },
        {
          "characterId": "cossus"
        }
      ]
    },
    {
      "id": "ascanius",
      "names": [
        "Ascanius"
      ],
      "relation": "Aeneas's son; mentioned in Rome's founding myths",
      "blurb": "Son of Aeneas; one variant of the founding myth makes Roma—the city's eponym—a Trojan lady married to Ascanius, placing Rome's origin in the Aeneid's direct male line.",
      "links": [
        {
          "characterId": "aeneas"
        }
      ]
    },
    {
      "id": "herodorus-ponticus",
      "names": [
        "Herodorus Ponticus",
        "Herodorus"
      ],
      "relation": "Mythographer who noted Hercules and the vulture",
      "blurb": "Heraclean mythographer who recorded that Hercules rejoiced whenever a vulture appeared to him at the start of any undertaking—cited to explain why Romans regard the vulture as the premier omen-bird in divination.",
      "links": [
        {
          "characterId": "hercules"
        }
      ]
    },
    {
      "id": "promathion",
      "names": [
        "Promathion"
      ],
      "relation": "Author of a history of Italy; Tarchetius story",
      "blurb": "Compiled a History of Italy in which he recorded the strange birth-legend of Tarchetius the Alban king—the rival founding myth involving a hearth-phallus that Plutarch presents as an alternative to the Mars-and-Rhea tradition.",
      "links": [
        {
          "characterId": "tarchetius"
        }
      ]
    },
    {
      "id": "teratius",
      "names": [
        "Teratius"
      ],
      "relation": "Tarchetius's agent who spared the twins",
      "blurb": "The man to whom Tarchetius handed the twin infants with orders to destroy them; instead Teratius carried them to the river bank, where a wolf suckled them until a cowherd found them.",
      "links": [
        {
          "characterId": "tarchetius"
        },
        {
          "characterId": "faustulus"
        }
      ]
    },
    {
      "id": "plistinus",
      "names": [
        "Plistinus"
      ],
      "relation": "Faustulus's brother; foster-uncle of Romulus",
      "blurb": "Brother of the shepherd Faustulus who helped raise Romulus and Remus; he too was killed in the scuffle at the new city's walls when Remus leaped over them in contempt.",
      "links": [
        {
          "characterId": "faustulus"
        },
        {
          "characterId": "remus"
        },
        {
          "characterId": "celer"
        }
      ]
    },
    {
      "id": "antimachus",
      "names": [
        "Antimachus the Teian",
        "Antimachus"
      ],
      "relation": "Teian poet whose eclipse fixes Rome's founding date",
      "blurb": "Archaic poet of Teos; the solar eclipse he recorded in the third year of the sixth Olympiad is the astronomical anchor Plutarch mentions for the traditional date on which Romulus laid Rome's first stone.",
      "links": [
        {
          "characterId": "romulus"
        }
      ]
    },
    {
      "id": "metellus",
      "names": [
        "Quintus Metellus",
        "Metellus"
      ],
      "relation": "Roman commander who gained the nickname Celer",
      "blurb": "Quintus Metellus who earned the cognomen Celer by producing a gladiatorial show in record time after his father's funeral—cited to explain how the Roman word Celeres, originally Romulus's bodyguard, became a general term for swiftness.",
      "links": [
        {
          "characterId": "celer"
        }
      ]
    },
    {
      "id": "philotis",
      "names": [
        "Philotis",
        "Tutola"
      ],
      "relation": "Handmaid who saved Rome from the Latin ruse",
      "blurb": "A servant-maid (called Philotis or, in another version, Tutola) who devised the stratagem of sending maid-servants disguised as free virgins to the Latin commander Postumius, then lit a torch as a signal for the Romans to fall on him.",
      "links": [
        {
          "characterId": "postumius-rom"
        }
      ]
    },
    {
      "id": "simylus",
      "names": [
        "Simylus"
      ],
      "relation": "Poet who wrongly said Tarpeia betrayed to the Gauls",
      "blurb": "Poet who spun a fanciful variant in which Tarpeia was in love with a Gallic king rather than with Sabine gold—an error Plutarch dismisses as 'mere folly.'",
      "links": [
        {
          "characterId": "tarpeia"
        }
      ]
    },
    {
      "id": "sulpicius-galba",
      "names": [
        "Sulpicius Galba",
        "Sulpicius"
      ],
      "relation": "Roman historian cited by Juba on Tarpeius",
      "blurb": "Roman writer whose account of Tarpeius being found guilty of treason is preserved through Juba; Plutarch invokes him to show that the father of the treacherous Tarpeia was himself prosecuted and convicted.",
      "links": [
        {
          "characterId": "tarpeius"
        },
        {
          "characterId": "juba"
        }
      ]
    },
    {
      "id": "rhymitalces",
      "names": [
        "Rhymitalces"
      ],
      "relation": "Thracian prince; recipient of Caesar's famous quip",
      "blurb": "A Thracian prince to whom Julius Caesar reportedly said he loved the treason but hated the traitor—cited alongside Antigonus's identical saying to illuminate the universal contempt for Tarpeia even among those who benefited from her betrayal.",
      "links": [
        {
          "characterId": "caesar-r"
        },
        {
          "characterId": "tarpeia"
        }
      ]
    },
    {
      "id": "lucius-hostius",
      "names": [
        "Lucius Hostius"
      ],
      "relation": "First parricide in Roman history",
      "blurb": "Roman citizen recorded as the first person ever to commit parricide in Rome—after nearly six centuries in which no such crime occurred, his act came only after the Hannibalic wars shattered the old moral fabric.",
      "links": [
        {
          "characterId": "romulus"
        }
      ]
    },
    {
      "id": "aeschylus",
      "names": [
        "Aeschylus"
      ],
      "relation": "Playwright quoted for eagles killing their own kind",
      "blurb": "Athenian tragedian; Plutarch quotes his verse about eagles and owls preying on creatures of their own species to explain why Romans prefer the vulture as an omen-bird—it alone never kills its kindred.",
      "links": [
        {
          "characterId": "herodorus-ponticus"
        }
      ]
    },
    {
      "id": "lavinia",
      "names": [
        "Lavinia"
      ],
      "relation": "Aeneas's wife in the Alban genealogy",
      "blurb": "Daughter of the Latin king Latinus who married Aeneas and gave her name to Lavinium; in one founding myth the twins' line runs through Aemilia, who was Aeneas's daughter by Lavinia.",
      "links": [
        {
          "characterId": "aeneas"
        },
        {
          "characterId": "ascanius"
        }
      ]
    },
    {
      "id": "publicola-r",
      "names": [
        "Publicola"
      ],
      "relation": "Co-founder of the Republic; first to ride in triumph",
      "blurb": "Publius Valerius Publicola, Rome's great republican lawgiver; one tradition credits him rather than Tarquinius with first riding in triumph—cited when Plutarch surveys conflicting accounts of the ceremony Romulus invented on foot.",
      "links": [
        {
          "characterId": "tarquinius-priscus"
        },
        {
          "characterId": "publicola-life",
          "label": "Poplicola's Life",
          "workId": "poplicola"
        }
      ]
    },
    {
      "id": "phorbas-rom",
      "names": [
        "Phorbas"
      ],
      "relation": "Dexithea's father in one founding legend",
      "blurb": "In one variant of the founding myth, Dexithea daughter of Phorbas was the mother of Romulus by Aeneas—a genealogy connecting the Latin founder tradition to an otherwise obscure Greek name.",
      "links": [
        {
          "characterId": "dexithea"
        }
      ]
    },
    {
      "id": "zenodotus-troez",
      "names": [
        "Zenodotus the Troezenian",
        "Zenodotus"
      ],
      "relation": "Historian who gave an account of Tarpeia",
      "blurb": "Historian from Troezen who told a version of the Tarpeia story; Plutarch cites him among the sources whose accounts of the Capitol's betrayal he weighs and largely rejects.",
      "links": [
        {
          "characterId": "tarpeia"
        },
        {
          "characterId": "simylus"
        }
      ]
    },
    {
      "id": "dexithea",
      "names": [
        "Dexithea"
      ],
      "relation": "Phorbas's daughter; a legendary mother of Romulus",
      "blurb": "In one founding variant, daughter of Phorbas and the woman Aeneas took as the mother of Romulus—an alternative birth-legend preserved among the many conflicting traditions Plutarch catalogues at the opening of the Life.",
      "links": [
        {
          "characterId": "phorbas-rom"
        },
        {
          "characterId": "aeneas"
        }
      ]
    },
    {
      "id": "aemilia-rom",
      "names": [
        "Aemilia"
      ],
      "relation": "Legendary daughter of Aeneas; mother of Romulus in one myth",
      "blurb": "In another founding variant, Aemilia—daughter of Aeneas by Lavinia—was said to have conceived Romulus by the god Mars; a tradition linking Rome's founder through Lavinia's lineage directly to Aeneas and divine parentage.",
      "links": [
        {
          "characterId": "aeneas"
        },
        {
          "characterId": "lavinia"
        },
        {
          "characterId": "mars"
        }
      ]
    },
    {
      "id": "latinus",
      "names": [
        "Latinus"
      ],
      "relation": "Son of Telemachus; Roma's husband in one legend",
      "blurb": "In one founding variant, Roma daughter of the Trojan woman was married to Latinus—son of Telemachus—and became the mother of Romulus; a genealogy threading the Romans back through Ulysses as well as Aeneas.",
      "links": [
        {
          "characterId": "telemachus-rom"
        },
        {
          "characterId": "aeneas"
        }
      ]
    },
    {
      "id": "telemachus-rom",
      "names": [
        "Telemachus"
      ],
      "relation": "Son of Odysseus; Latinus's father in one founding myth",
      "blurb": "Homer's Telemachus appears in one alternative founding legend as the father of Latinus who wed Roma—a tradition connecting Rome's origins to the Odyssey's hero as well as the Iliad's Aeneas.",
      "links": [
        {
          "characterId": "latinus"
        }
      ]
    }
  ],
  "locations": [
    {
      "id": "alba",
      "names": [
        "Alba"
      ],
      "relation": "Alba Longa of his birth",
      "modern": "Castel Gandolfo / Alban Hills",
      "lat": 41.75,
      "lon": 12.65,
      "presence": "visited",
      "visitKind": "city",
      "visitOrder": 1,
      "travel": "land",
      "blurb": "Royal Alba of Numitor and Amulius—where the twins were born before the basket on the Tiber."
    },
    {
      "id": "tiber",
      "names": [
        "Tiber"
      ],
      "relation": "River of exposure and return",
      "modern": "Tiber River, Italy",
      "lat": 41.9,
      "lon": 12.48,
      "presence": "visited",
      "visitKind": "crossing",
      "visitOrder": 2,
      "travel": "land",
      "blurb": "Set adrift, caught at the flood’s edge by Faustulus—Rome’s river as cradle before the Palatine."
    },
    {
      "id": "palatine",
      "names": [
        "Palatine"
      ],
      "relation": "Hill of the founding",
      "modern": "Palatine Hill, Rome",
      "lat": 41.889,
      "lon": 12.487,
      "presence": "visited",
      "visitKind": "foundation",
      "visitOrder": 3,
      "travel": "land",
      "blurb": "He chose the Palatine for the new city—walls, rites, and the quarrel that killed Remus."
    },
    {
      "id": "rome",
      "names": [
        "Rome"
      ],
      "relation": "City he founded",
      "modern": "Rome, Italy",
      "lat": 41.89,
      "lon": 12.49,
      "presence": "visited",
      "visitKind": "foundation",
      "visitOrder": 4,
      "travel": "land",
      "blurb": "Named for him in the legend—asylum, tribes, and the calendar of a city that outgrew the hill."
    },
    {
      "id": "crustumerium",
      "names": [
        "Crustumerium"
      ],
      "relation": "Early Latin war",
      "modern": "north of Rome, Latium",
      "lat": 42.05,
      "lon": 12.6,
      "presence": "visited",
      "visitKind": "battle",
      "visitOrder": 5,
      "travel": "land",
      "blurb": "Among the first towns he took in the wars that fed Rome’s strength and Sabine entanglement."
    },
    {
      "id": "fidenae",
      "names": [
        "Fidenae"
      ],
      "relation": "Neighbor town in early wars",
      "modern": "near Villa Spada / Fidene",
      "lat": 41.98,
      "lon": 12.51,
      "presence": "visited",
      "visitKind": "battle",
      "visitOrder": 6,
      "travel": "land",
      "blurb": "Fidenae felt the new city’s arms—another step in Romulus’s ring of conquest around the Tiber."
    },
    {
      "id": "capitol",
      "names": [
        "Capitol",
        "Capitoline"
      ],
      "relation": "Hill of the asylum and Jupiter",
      "modern": "Capitoline Hill, Rome",
      "lat": 41.893,
      "lon": 12.483,
      "presence": "visited",
      "visitKind": "city",
      "visitOrder": 7,
      "travel": "land",
      "blurb": "He opened an asylum on the Capitol—refuge that swelled Rome’s people and its peril."
    },
    {
      "id": "aventine",
      "names": [
        "Aventine"
      ],
      "relation": "Remus’s augury hill",
      "modern": "Aventine Hill, Rome",
      "lat": 41.883,
      "lon": 12.475,
      "presence": "named",
      "blurb": "Remus took the Aventine for his birds—the rival hill in the founding omen."
    },
    {
      "id": "lavinium",
      "names": [
        "Lavinium"
      ],
      "relation": "Aeneas’s town in the lineage",
      "modern": "Pratica di Mare area",
      "lat": 41.66,
      "lon": 12.48,
      "presence": "named",
      "blurb": "City of Aeneas and Lavinia in the ancestry that links Troy’s remnant to Alba and Rome."
    },
    {
      "id": "laurentum",
      "names": [
        "Laurentum"
      ],
      "relation": "Latin coast of the Aeneas tale",
      "modern": "Laurentine coast, Latium",
      "lat": 41.7,
      "lon": 12.35,
      "presence": "named",
      "blurb": "Named with Lavinium in the Latin shore-story behind Romulus’s Alban line."
    },
    {
      "id": "gabii",
      "names": [
        "Gabii"
      ],
      "relation": "Latin town in early Rome’s orbit",
      "modern": "near Osteria dell’Osa",
      "lat": 41.89,
      "lon": 12.72,
      "presence": "named",
      "blurb": "Counted among Latin neighbors as Rome’s power thickened east of the city."
    }
  ]
}
